Metadata-Version: 2.1
Name: FundPrediction
Version: 1.0
Summary: FundPrediction Information Search Engine
Home-page: https://blog.csdn.net/weixin_43456810
Author: Sherlock Xu
Author-email: sherlockjjobs@icloud.com
License: LGPL
Platform: UNKNOWN
